derpibooru/__init__.py
derpibooru/comment.py
derpibooru/comments.py
derpibooru/filters.py
derpibooru/forums.py
derpibooru/galleries.py
derpibooru/gallery.py
derpibooru/helpers.py
derpibooru/image.py
derpibooru/post.py
derpibooru/post_image.py
derpibooru/posts.py
derpibooru/profile.py
derpibooru/query.py
derpibooru/request.py
derpibooru/search.py
derpibooru/sort.py
derpibooru/tag.py
derpibooru/tags.py
derpibooru/user.py
tests/__init__.py
tests/test_random_parameters.py
tests/test_search_live.py
tests/test_typical_usage.py
DerPyBooruPhi-0.10.6.dist-info/LICENSE.txt
DerPyBooruPhi-0.10.6.dist-info/METADATA
DerPyBooruPhi-0.10.6.dist-info/WHEEL
DerPyBooruPhi-0.10.6.dist-info/top_level.txt
DerPyBooruPhi-0.10.6.dist-info/RECORD
